{
    "filename": "iso_sheet_66.png",
    "components": {
        "title_block": [
            800,
            1000,
            1560,
            1160
        ],
        "notes": [
            100,
            960,
            480,
            1140
        ],
        "gdt_features": [
            {
                "symbol": "Profile of a Surface",
                "tolerance": "\u23000.29 (M)",
                "datums": [
                    "E",
                    "B"
                ],
                "bbox_pixels": [
                    599,
                    414,
                    929,
                    474
                ]
            },
            {
                "symbol": "Symmetry",
                "tolerance": "0.03",
                "datums": [
                    "B"
                ],
                "bbox_pixels": [
                    248,
                    673,
                    518,
                    733
                ]
            },
            {
                "symbol": "Profile of a Surface",
                "tolerance": "0.48 (L)",
                "datums": [
                    "B"
                ],
                "bbox_pixels": [
                    983,
                    269,
                    1253,
                    329
                ]
            },
            {
                "symbol": "Profile of a Line",
                "tolerance": "0.39",
                "datums": [
                    "B"
                ],
                "bbox_pixels": [
                    669,
                    692,
                    939,
                    752
                ]
            }
        ]
    }
}