{
    "filename": "iso_sheet_46.png",
    "components": {
        "title_block": [
            800,
            1000,
            1560,
            1160
        ],
        "notes": [
            100,
            960,
            480,
            1140
        ],
        "gdt_features": [
            {
                "symbol": "Parallelism",
                "tolerance": "\u23000.15 (M)",
                "datums": [
                    "A",
                    "D",
                    "F"
                ],
                "bbox_pixels": [
                    362,
                    632,
                    752,
                    692
                ]
            },
            {
                "symbol": "Straightness",
                "tolerance": "\u23000.34 (M)",
                "datums": [
                    "C"
                ],
                "bbox_pixels": [
                    337,
                    543,
                    607,
                    603
                ]
            },
            {
                "symbol": "Symmetry",
                "tolerance": "\u23000.22 (L)",
                "datums": [
                    "D"
                ],
                "bbox_pixels": [
                    206,
                    122,
                    476,
                    182
                ]
            },
            {
                "symbol": "Parallelism",
                "tolerance": "\u23000.44",
                "datums": [
                    "E",
                    "D"
                ],
                "bbox_pixels": [
                    149,
                    202,
                    479,
                    262
                ]
            }
        ]
    }
}